<?xml version="1.0" encoding="utf-8"?>
<!DOCTYPE hibernate-mapping PUBLIC "-//Hibernate/Hibernate Mapping DTD 3.0//EN"
"http://hibernate.sourceforge.net/hibernate-mapping-3.0.dtd">
<!-- 
    Mapping file autogenerated by MyEclipse Persistence Tools
-->
<hibernate-mapping>
    <class name="com.evaluacionlinea.model.TipoCuestionario" table="tipocuestionario" 
		proxy="com.evaluacionlinea.model.TipoCuestionario">
        <id name="tcueId" type="java.lang.Integer">
            <column name="tcue_id" />
            <generator class="native"></generator>
        </id>
        <property name="nombre" type="java.lang.String">
            <column name="nombre" length="100" not-null="true" />
        </property>
        <property name="descripcion" type="java.lang.String">
            <column name="descripcion" length="200" />
        </property>
        <property name="activo" type="java.lang.Boolean">
            <column name="activo" not-null="true" />
        </property>
    </class>
</hibernate-mapping>
